{
  "ExportedBy": "StudioWeb",
  "BundleHash": "RACOEUSpPDd7Kp0JFTTvAMrV5P3ULjG9aEc5J91Cc",
  "Version": "1.0.0.0",
  "JitAssemblyCompilerCommands": [
    {
      "ProviderName": "CustomEntities",
      "BundleOptions": {
        "Hash": "yzvibfNnDmNTOx4S+/oGezUvTWZ/wPu27C7D/qho394=",
        "BundleName": "AG_Claim_Analysis_Core__content_agent_json_Input",
        "EntitiesBundle": {
          "Types": {
            "AG_Claim_Analysis_Core__content_agent_json_Input": {
              "Name": "AG_Claim_Analysis_Core__content_agent_json_Input",
              "Properties": [
                {
                  "Name": "claim_id",
                  "Type": {
                    "ClrType": "System.String, System.Private.CoreLib"
                  },
                  "Attributes": {
                    "Values": [
                      {
                        "Type": {
                          "ClrType": "Newtonsoft.Json.JsonPropertyAttribute, Newtonsoft.Json"
                        },
                        "ConstructorArguments": [
                          {
                            "Value": "\"claim_id\"",
                            "Type": {
                              "ClrType": "System.String, System.Private.CoreLib"
                            }
                          }
                        ],
                        "NamedArguments": []
                      },
                      {
                        "Type": {
                          "ClrType": "System.ComponentModel.DisplayNameAttribute, System.ComponentModel.Primitives"
                        },
                        "ConstructorArguments": [
                          {
                            "Value": "\"claim_id\"",
                            "Type": {
                              "ClrType": "System.String, System.Private.CoreLib"
                            }
                          }
                        ],
                        "NamedArguments": []
                      },
                      {
                        "Type": {
                          "ClrType": "System.ComponentModel.DataAnnotations.RequiredAttribute, System.ComponentModel.Annotations"
                        },
                        "ConstructorArguments": [],
                        "NamedArguments": []
                      }
                    ]
                  }
                },
                {
                  "Name": "document_text_bundle",
                  "Type": {
                    "ClrType": "System.String, System.Private.CoreLib"
                  },
                  "Attributes": {
                    "Values": [
                      {
                        "Type": {
                          "ClrType": "Newtonsoft.Json.JsonPropertyAttribute, Newtonsoft.Json"
                        },
                        "ConstructorArguments": [
                          {
                            "Value": "\"document_text_bundle\"",
                            "Type": {
                              "ClrType": "System.String, System.Private.CoreLib"
                            }
                          }
                        ],
                        "NamedArguments": []
                      },
                      {
                        "Type": {
                          "ClrType": "System.ComponentModel.DisplayNameAttribute, System.ComponentModel.Primitives"
                        },
                        "ConstructorArguments": [
                          {
                            "Value": "\"document_text_bundle\"",
                            "Type": {
                              "ClrType": "System.String, System.Private.CoreLib"
                            }
                          }
                        ],
                        "NamedArguments": []
                      },
                      {
                        "Type": {
                          "ClrType": "System.ComponentModel.DataAnnotations.RequiredAttribute, System.ComponentModel.Annotations"
                        },
                        "ConstructorArguments": [],
                        "NamedArguments": []
                      }
                    ]
                  }
                },
                {
                  "Name": "extraction_notes",
                  "Type": {
                    "ClrType": "System.String, System.Private.CoreLib"
                  },
                  "Attributes": {
                    "Values": [
                      {
                        "Type": {
                          "ClrType": "Newtonsoft.Json.JsonPropertyAttribute, Newtonsoft.Json"
                        },
                        "ConstructorArguments": [
                          {
                            "Value": "\"extraction_notes\"",
                            "Type": {
                              "ClrType": "System.String, System.Private.CoreLib"
                            }
                          }
                        ],
                        "NamedArguments": []
                      },
                      {
                        "Type": {
                          "ClrType": "System.ComponentModel.DisplayNameAttribute, System.ComponentModel.Primitives"
                        },
                        "ConstructorArguments": [
                          {
                            "Value": "\"extraction_notes\"",
                            "Type": {
                              "ClrType": "System.String, System.Private.CoreLib"
                            }
                          }
                        ],
                        "NamedArguments": []
                      }
                    ]
                  }
                },
                {
                  "Name": "knowledge_bundle",
                  "Type": {
                    "ClrType": "System.String, System.Private.CoreLib"
                  },
                  "Attributes": {
                    "Values": [
                      {
                        "Type": {
                          "ClrType": "Newtonsoft.Json.JsonPropertyAttribute, Newtonsoft.Json"
                        },
                        "ConstructorArguments": [
                          {
                            "Value": "\"knowledge_bundle\"",
                            "Type": {
                              "ClrType": "System.String, System.Private.CoreLib"
                            }
                          }
                        ],
                        "NamedArguments": []
                      },
                      {
                        "Type": {
                          "ClrType": "System.ComponentModel.DisplayNameAttribute, System.ComponentModel.Primitives"
                        },
                        "ConstructorArguments": [
                          {
                            "Value": "\"knowledge_bundle\"",
                            "Type": {
                              "ClrType": "System.String, System.Private.CoreLib"
                            }
                          }
                        ],
                        "NamedArguments": []
                      },
                      {
                        "Type": {
                          "ClrType": "System.ComponentModel.DataAnnotations.RequiredAttribute, System.ComponentModel.Annotations"
                        },
                        "ConstructorArguments": [],
                        "NamedArguments": []
                      }
                    ]
                  }
                },
                {
                  "Name": "knowledge_quality_hint",
                  "Type": {
                    "ClrType": "System.String, System.Private.CoreLib"
                  },
                  "Attributes": {
                    "Values": [
                      {
                        "Type": {
                          "ClrType": "Newtonsoft.Json.JsonPropertyAttribute, Newtonsoft.Json"
                        },
                        "ConstructorArguments": [
                          {
                            "Value": "\"knowledge_quality_hint\"",
                            "Type": {
                              "ClrType": "System.String, System.Private.CoreLib"
                            }
                          }
                        ],
                        "NamedArguments": []
                      },
                      {
                        "Type": {
                          "ClrType": "System.ComponentModel.DisplayNameAttribute, System.ComponentModel.Primitives"
                        },
                        "ConstructorArguments": [
                          {
                            "Value": "\"knowledge_quality_hint\"",
                            "Type": {
                              "ClrType": "System.String, System.Private.CoreLib"
                            }
                          }
                        ],
                        "NamedArguments": []
                      },
                      {
                        "Type": {
                          "ClrType": "System.ComponentModel.DataAnnotations.RequiredAttribute, System.ComponentModel.Annotations"
                        },
                        "ConstructorArguments": [],
                        "NamedArguments": []
                      }
                    ]
                  }
                }
              ],
              "Values": [],
              "BaseType": null
            }
          },
          "Metadata": {},
          "Version": 1
        }
      },
      "EntityAssemblyKey": {
        "Name": "UiPath.System.Activities.ViewModels.SWEntities.AG_Claim_Analysis_Core__content_agent_json_Input",
        "Hash": "eXp2aWJmTm5EbU5UT3g0Uysvb0dlelV2VFdaL3dQdTI3QzdEL3FobzM5ND0",
        "AssemblyName": "AG_Claim_Analysis_Co.U5gLC4lJZEP1zrzLMObiqj1"
      }
    },
    {
      "ProviderName": "CustomEntities",
      "BundleOptions": {
        "Hash": "f93K6zb3Ynk+58BfkIjuxsxfBcB4HdOwmoV/rWew8rc=",
        "BundleName": "AG_Claim_Analysis_Core__content_agent_json_Output",
        "EntitiesBundle": {
          "Types": {
            "AG_Claim_Analysis_Core__content_agent_json_Output": {
              "Name": "AG_Claim_Analysis_Core__content_agent_json_Output",
              "Properties": [
                {
                  "Name": "analysis_confidence",
                  "Type": {
                    "ClrType": "System.Double, System.Private.CoreLib"
                  },
                  "Attributes": {
                    "Values": [
                      {
                        "Type": {
                          "ClrType": "Newtonsoft.Json.JsonPropertyAttribute, Newtonsoft.Json"
                        },
                        "ConstructorArguments": [
                          {
                            "Value": "\"analysis_confidence\"",
                            "Type": {
                              "ClrType": "System.String, System.Private.CoreLib"
                            }
                          }
                        ],
                        "NamedArguments": []
                      },
                      {
                        "Type": {
                          "ClrType": "System.ComponentModel.DisplayNameAttribute, System.ComponentModel.Primitives"
                        },
                        "ConstructorArguments": [
                          {
                            "Value": "\"analysis_confidence\"",
                            "Type": {
                              "ClrType": "System.String, System.Private.CoreLib"
                            }
                          }
                        ],
                        "NamedArguments": []
                      },
                      {
                        "Type": {
                          "ClrType": "System.ComponentModel.DataAnnotations.RequiredAttribute, System.ComponentModel.Annotations"
                        },
                        "ConstructorArguments": [],
                        "NamedArguments": []
                      }
                    ]
                  }
                },
                {
                  "Name": "category",
                  "Type": {
                    "ClrType": "System.String, System.Private.CoreLib"
                  },
                  "Attributes": {
                    "Values": [
                      {
                        "Type": {
                          "ClrType": "Newtonsoft.Json.JsonPropertyAttribute, Newtonsoft.Json"
                        },
                        "ConstructorArguments": [
                          {
                            "Value": "\"category\"",
                            "Type": {
                              "ClrType": "System.String, System.Private.CoreLib"
                            }
                          }
                        ],
                        "NamedArguments": []
                      },
                      {
                        "Type": {
                          "ClrType": "System.ComponentModel.DisplayNameAttribute, System.ComponentModel.Primitives"
                        },
                        "ConstructorArguments": [
                          {
                            "Value": "\"category\"",
                            "Type": {
                              "ClrType": "System.String, System.Private.CoreLib"
                            }
                          }
                        ],
                        "NamedArguments": []
                      },
                      {
                        "Type": {
                          "ClrType": "System.ComponentModel.DataAnnotations.RequiredAttribute, System.ComponentModel.Annotations"
                        },
                        "ConstructorArguments": [],
                        "NamedArguments": []
                      }
                    ]
                  }
                },
                {
                  "Name": "category_confidence",
                  "Type": {
                    "ClrType": "System.Double, System.Private.CoreLib"
                  },
                  "Attributes": {
                    "Values": [
                      {
                        "Type": {
                          "ClrType": "Newtonsoft.Json.JsonPropertyAttribute, Newtonsoft.Json"
                        },
                        "ConstructorArguments": [
                          {
                            "Value": "\"category_confidence\"",
                            "Type": {
                              "ClrType": "System.String, System.Private.CoreLib"
                            }
                          }
                        ],
                        "NamedArguments": []
                      },
                      {
                        "Type": {
                          "ClrType": "System.ComponentModel.DisplayNameAttribute, System.ComponentModel.Primitives"
                        },
                        "ConstructorArguments": [
                          {
                            "Value": "\"category_confidence\"",
                            "Type": {
                              "ClrType": "System.String, System.Private.CoreLib"
                            }
                          }
                        ],
                        "NamedArguments": []
                      },
                      {
                        "Type": {
                          "ClrType": "System.ComponentModel.DataAnnotations.RequiredAttribute, System.ComponentModel.Annotations"
                        },
                        "ConstructorArguments": [],
                        "NamedArguments": []
                      }
                    ]
                  }
                },
                {
                  "Name": "claim_summary",
                  "Type": {
                    "ClrType": "System.String, System.Private.CoreLib"
                  },
                  "Attributes": {
                    "Values": [
                      {
                        "Type": {
                          "ClrType": "Newtonsoft.Json.JsonPropertyAttribute, Newtonsoft.Json"
                        },
                        "ConstructorArguments": [
                          {
                            "Value": "\"claim_summary\"",
                            "Type": {
                              "ClrType": "System.String, System.Private.CoreLib"
                            }
                          }
                        ],
                        "NamedArguments": []
                      },
                      {
                        "Type": {
                          "ClrType": "System.ComponentModel.DisplayNameAttribute, System.ComponentModel.Primitives"
                        },
                        "ConstructorArguments": [
                          {
                            "Value": "\"claim_summary\"",
                            "Type": {
                              "ClrType": "System.String, System.Private.CoreLib"
                            }
                          }
                        ],
                        "NamedArguments": []
                      },
                      {
                        "Type": {
                          "ClrType": "System.ComponentModel.DataAnnotations.RequiredAttribute, System.ComponentModel.Annotations"
                        },
                        "ConstructorArguments": [],
                        "NamedArguments": []
                      }
                    ]
                  }
                },
                {
                  "Name": "documents_complete",
                  "Type": {
                    "ClrType": "System.Boolean, System.Private.CoreLib"
                  },
                  "Attributes": {
                    "Values": [
                      {
                        "Type": {
                          "ClrType": "Newtonsoft.Json.JsonPropertyAttribute, Newtonsoft.Json"
                        },
                        "ConstructorArguments": [
                          {
                            "Value": "\"documents_complete\"",
                            "Type": {
                              "ClrType": "System.String, System.Private.CoreLib"
                            }
                          }
                        ],
                        "NamedArguments": []
                      },
                      {
                        "Type": {
                          "ClrType": "System.ComponentModel.DisplayNameAttribute, System.ComponentModel.Primitives"
                        },
                        "ConstructorArguments": [
                          {
                            "Value": "\"documents_complete\"",
                            "Type": {
                              "ClrType": "System.String, System.Private.CoreLib"
                            }
                          }
                        ],
                        "NamedArguments": []
                      },
                      {
                        "Type": {
                          "ClrType": "System.ComponentModel.DataAnnotations.RequiredAttribute, System.ComponentModel.Annotations"
                        },
                        "ConstructorArguments": [],
                        "NamedArguments": []
                      }
                    ]
                  }
                },
                {
                  "Name": "eligibility_reason",
                  "Type": {
                    "ClrType": "System.String, System.Private.CoreLib"
                  },
                  "Attributes": {
                    "Values": [
                      {
                        "Type": {
                          "ClrType": "Newtonsoft.Json.JsonPropertyAttribute, Newtonsoft.Json"
                        },
                        "ConstructorArguments": [
                          {
                            "Value": "\"eligibility_reason\"",
                            "Type": {
                              "ClrType": "System.String, System.Private.CoreLib"
                            }
                          }
                        ],
                        "NamedArguments": []
                      },
                      {
                        "Type": {
                          "ClrType": "System.ComponentModel.DisplayNameAttribute, System.ComponentModel.Primitives"
                        },
                        "ConstructorArguments": [
                          {
                            "Value": "\"eligibility_reason\"",
                            "Type": {
                              "ClrType": "System.String, System.Private.CoreLib"
                            }
                          }
                        ],
                        "NamedArguments": []
                      },
                      {
                        "Type": {
                          "ClrType": "System.ComponentModel.DataAnnotations.RequiredAttribute, System.ComponentModel.Annotations"
                        },
                        "ConstructorArguments": [],
                        "NamedArguments": []
                      }
                    ]
                  }
                },
                {
                  "Name": "eligible",
                  "Type": {
                    "ClrType": "System.Boolean, System.Private.CoreLib"
                  },
                  "Attributes": {
                    "Values": [
                      {
                        "Type": {
                          "ClrType": "Newtonsoft.Json.JsonPropertyAttribute, Newtonsoft.Json"
                        },
                        "ConstructorArguments": [
                          {
                            "Value": "\"eligible\"",
                            "Type": {
                              "ClrType": "System.String, System.Private.CoreLib"
                            }
                          }
                        ],
                        "NamedArguments": []
                      },
                      {
                        "Type": {
                          "ClrType": "System.ComponentModel.DisplayNameAttribute, System.ComponentModel.Primitives"
                        },
                        "ConstructorArguments": [
                          {
                            "Value": "\"eligible\"",
                            "Type": {
                              "ClrType": "System.String, System.Private.CoreLib"
                            }
                          }
                        ],
                        "NamedArguments": []
                      },
                      {
                        "Type": {
                          "ClrType": "System.ComponentModel.DataAnnotations.RequiredAttribute, System.ComponentModel.Annotations"
                        },
                        "ConstructorArguments": [],
                        "NamedArguments": []
                      }
                    ]
                  }
                },
                {
                  "Name": "key_document_facts",
                  "Type": {
                    "ClrType": "System.String, System.Private.CoreLib"
                  },
                  "Attributes": {
                    "Values": [
                      {
                        "Type": {
                          "ClrType": "Newtonsoft.Json.JsonPropertyAttribute, Newtonsoft.Json"
                        },
                        "ConstructorArguments": [
                          {
                            "Value": "\"key_document_facts\"",
                            "Type": {
                              "ClrType": "System.String, System.Private.CoreLib"
                            }
                          }
                        ],
                        "NamedArguments": []
                      },
                      {
                        "Type": {
                          "ClrType": "System.ComponentModel.DisplayNameAttribute, System.ComponentModel.Primitives"
                        },
                        "ConstructorArguments": [
                          {
                            "Value": "\"key_document_facts\"",
                            "Type": {
                              "ClrType": "System.String, System.Private.CoreLib"
                            }
                          }
                        ],
                        "NamedArguments": []
                      },
                      {
                        "Type": {
                          "ClrType": "System.ComponentModel.DataAnnotations.RequiredAttribute, System.ComponentModel.Annotations"
                        },
                        "ConstructorArguments": [],
                        "NamedArguments": []
                      }
                    ]
                  }
                },
                {
                  "Name": "missing_documents",
                  "Type": {
                    "ClrType": "System.String, System.Private.CoreLib"
                  },
                  "Attributes": {
                    "Values": [
                      {
                        "Type": {
                          "ClrType": "Newtonsoft.Json.JsonPropertyAttribute, Newtonsoft.Json"
                        },
                        "ConstructorArguments": [
                          {
                            "Value": "\"missing_documents\"",
                            "Type": {
                              "ClrType": "System.String, System.Private.CoreLib"
                            }
                          }
                        ],
                        "NamedArguments": []
                      },
                      {
                        "Type": {
                          "ClrType": "System.ComponentModel.DisplayNameAttribute, System.ComponentModel.Primitives"
                        },
                        "ConstructorArguments": [
                          {
                            "Value": "\"missing_documents\"",
                            "Type": {
                              "ClrType": "System.String, System.Private.CoreLib"
                            }
                          }
                        ],
                        "NamedArguments": []
                      },
                      {
                        "Type": {
                          "ClrType": "System.ComponentModel.DataAnnotations.RequiredAttribute, System.ComponentModel.Annotations"
                        },
                        "ConstructorArguments": [],
                        "NamedArguments": []
                      }
                    ]
                  }
                },
                {
                  "Name": "request_message",
                  "Type": {
                    "ClrType": "System.String, System.Private.CoreLib"
                  },
                  "Attributes": {
                    "Values": [
                      {
                        "Type": {
                          "ClrType": "Newtonsoft.Json.JsonPropertyAttribute, Newtonsoft.Json"
                        },
                        "ConstructorArguments": [
                          {
                            "Value": "\"request_message\"",
                            "Type": {
                              "ClrType": "System.String, System.Private.CoreLib"
                            }
                          }
                        ],
                        "NamedArguments": []
                      },
                      {
                        "Type": {
                          "ClrType": "System.ComponentModel.DisplayNameAttribute, System.ComponentModel.Primitives"
                        },
                        "ConstructorArguments": [
                          {
                            "Value": "\"request_message\"",
                            "Type": {
                              "ClrType": "System.String, System.Private.CoreLib"
                            }
                          }
                        ],
                        "NamedArguments": []
                      },
                      {
                        "Type": {
                          "ClrType": "System.ComponentModel.DataAnnotations.RequiredAttribute, System.ComponentModel.Annotations"
                        },
                        "ConstructorArguments": [],
                        "NamedArguments": []
                      }
                    ]
                  }
                }
              ],
              "Values": [],
              "BaseType": null
            }
          },
          "Metadata": {},
          "Version": 1
        }
      },
      "EntityAssemblyKey": {
        "Name": "UiPath.System.Activities.ViewModels.SWEntities.AG_Claim_Analysis_Core__content_agent_json_Output",
        "Hash": "ZjkzSzZ6YjNZbmsrNThCZmtJanV4c3hmQmNCNEhkT3dtb1YvcldldzhyYz0",
        "AssemblyName": "AG_Claim_Analysis_Co.wL4gW2QgqWR1bwKrSvrd6R1"
      }
    }
  ]
}